[
{"json": [{"staffid": "ali.abbas", "givenname": "Ali", "surname": "Abbas", "urlid": "ali.abbas", "profileUrl": null}, {"staffid": "fatima.afzal", "givenname": "Fatima", "surname": "Afzal", "urlid": "fatima.afzal", "profileUrl": null}, {"staffid": "euijoon.ahn", "givenname": "Euijoon", "surname": "Ahn", "urlid": "euijoon.ahn", "profileUrl": null}, {"staffid": "david.airey", "givenname": "David", "surname": "Airey", "urlid": "david.airey", "profileUrl": null}, {"staffid": "behnam.akhavan", "givenname": "Behnam", "surname": "Akhavan", "urlid": "behnam.akhavan", "profileUrl": null}, {"staffid": "tonima.ali", "givenname": "Tonima", "surname": "Ali", "urlid": "tonima.ali", "profileUrl": null}, {"staffid": "fernando.alonso", "givenname": "Fernando", "surname": "Alonso-Marroquin", "urlid": "fernando.alonso", "profileUrl": null}, {"staffid": "ali.amin", "givenname": "Ali", "surname": "Amin", "urlid": "ali.amin", "profileUrl": null}, {"staffid": "xianghai.an", "givenname": "Xianghai", "surname": "An", "urlid": "xianghai.an", "profileUrl": null}, {"staffid": "ali.anaissi", "givenname": "Ali", "surname": "Anaissi", "urlid": "ali.anaissi", "profileUrl": null}, {"staffid": "karyne.ang", "givenname": "Karyne", "surname": "Ang", "urlid": "karyne.ang", "profileUrl": null}, {"staffid": "wije.ariyaratne", "givenname": "Wije", "surname": "Ariyaratne", "urlid": "wije.ariyaratne", "profileUrl": null}, {"staffid": "steven.armfield", "givenname": "Steven", "surname": "Armfield", "urlid": "steven.armfield", "profileUrl": null}, {"staffid": "javid.atai", "givenname": "Javid", "surname": "Atai", "urlid": "javid.atai", "profileUrl": null}, {"staffid": "tim.bailey", "givenname": "Tim", "surname": "Bailey", "urlid": "tim.bailey", "profileUrl": null}, {"staffid": "james.baker", "givenname": "James", "surname": "Baker", "urlid": "james.baker", "profileUrl": null}, {"staffid": "marzena.baker", "givenname": "Marzena", "surname": "Baker", "urlid": "marzena.baker", "profileUrl": null}, {"staffid": "mehala.balamurali", "givenname": "Mehala", "surname": "Balamurali", "urlid": "mehala.balamurali", "profileUrl": null}, {"staffid": "mark.baldry", "givenname": "Mark", "surname": "Baldry", "urlid": "mark.baldry", "profileUrl": null}, {"staffid": "adrian.ball", "givenname": "Adrian", "surname": "Ball", "urlid": "adrian.ball", "profileUrl": null}, {"staffid": "mike.bambach", "givenname": "Mike", "surname": "Bambach", "urlid": "mike.bambach", "profileUrl": null}, {"staffid": "wei.bao", "givenname": "Wei", "surname": "Bao", "urlid": "wei.bao", "profileUrl": null}, {"staffid": "lucas.barcelos", "givenname": "Lucas", "surname": "Barcelos De Oliveira", "urlid": "lucas.barcelos", "profileUrl": null}, {"staffid": "geoff.barton", "givenname": "Geoffrey", "surname": "Barton", "urlid": "geoff.barton", "profileUrl": null}, {"staffid": "asher.bender", "givenname": "Asher", "surname": "Bender", "urlid": "asher.bender", "profileUrl": null}, {"staffid": "julie.berrioperez", "givenname": "Stephany", "surname": "Berrio Perez", "urlid": "julie.berrioperez", "profileUrl": null}, {"staffid": "lei.bi", "givenname": "Lei", "surname": "Bi", "urlid": "lei.bi", "profileUrl": null}, {"staffid": "marcela.bilek", "givenname": "Marcela", "surname": "Bilek", "urlid": "marcela.bilek", "profileUrl": null}, {"staffid": "david.boland", "givenname": "David", "surname": "Boland", "urlid": "david.boland", "profileUrl": null}, {"staffid": "athman.bouguettaya", "givenname": "Athman", "surname": "Bouguettaya", "urlid": "athman.bouguettaya", "profileUrl": null}, {"staffid": "andrew.breen", "givenname": "Andrew", "surname": "Breen", "urlid": "andrew.breen", "profileUrl": null}, {"staffid": "paul.briozzo", "givenname": "Paul", "surname": "Briozzo", "urlid": "paul.briozzo", "profileUrl": null}, {"staffid": "graham.brooker", "givenname": "Graham", "surname": "Brooker", "urlid": "graham.brooker", "profileUrl": null}, {"staffid": "mitch.bryson", "givenname": "Mitch", "surname": "Bryson", "urlid": "mitch.bryson", "profileUrl": null}, {"staffid": "roman.buckow", "givenname": "Roman", "surname": "Buckow", "urlid": "roman.buckow", "profileUrl": null}, {"staffid": "robert.busby", "givenname": "Robert", "surname": "Busby", "urlid": "robert.busby", "profileUrl": null}, {"staffid": "tom.cai", "givenname": "Weidong", "surname": "Cai", "urlid": "tom.cai", "profileUrl": null}, {"staffid": "julie.cairney", "givenname": "Julie", "surname": "Cairney", "urlid": "julie.cairney", "profileUrl": null}, {"staffid": "fernando.calamante", "givenname": "Fernando", "surname": "Calamante", "urlid": "fernando.calamante", "profileUrl": null}, {"staffid": "clement.canonne", "givenname": "Clement", "surname": "Canonne", "urlid": "clement.canonne", "profileUrl": null}, {"staffid": "michel.chaaya", "givenname": "Michel", "surname": "Chaaya", "urlid": "michel.chaaya", "profileUrl": null}, {"staffid": "amin.chabchoub", "givenname": "Amin", "surname": "Chabchoub", "urlid": "amin.chabchoub", "profileUrl": null}, {"staffid": "m.chamanbaz", "givenname": "Mohammadreza", "surname": "Chamanbaz", "urlid": "m.chamanbaz", "profileUrl": null}, {"staffid": "li.chang", "givenname": "Li", "surname": "Chang", "urlid": "li.chang", "profileUrl": null}, {"staffid": "lijun.chang", "givenname": "Lijun", "surname": "Chang", "urlid": "lijun.chang", "profileUrl": null}, {"staffid": "kapil.chauhan", "givenname": "Kapil", "surname": "Chauhan", "urlid": "kapil.chauhan", "profileUrl": null}, {"staffid": "yi-sheng.chen", "givenname": "Yi-Sheng (Eason)", "surname": "Chen", "urlid": "yi-sheng.chen", "profileUrl": null}, {"staffid": "yche2081", "givenname": "Yuan", "surname": "Chen", "urlid": "yche2081", "profileUrl": null}, {"staffid": "yuan.chen", "givenname": "Yuan", "surname": "Chen", "urlid": "yuan.chen", "profileUrl": null}, {"staffid": "zhe.chen1", "givenname": "Zhe", "surname": "Chen", "urlid": "zhe.chen1", "profileUrl": null}, {"staffid": "zhenghao.chen", "givenname": "Zhenghao", "surname": "Chen", "urlid": "zhenghao.chen", "profileUrl": null}, {"staffid": "z.chen", "givenname": "Zibin", "surname": "Chen", "urlid": "z.chen", "profileUrl": null}, {"staffid": "anna.chlingaryan", "givenname": "Anna", "surname": "Chlingaryan", "urlid": "anna.chlingaryan", "profileUrl": null}, {"staffid": "ken.chung", "givenname": "Ken", "surname": "Chung", "urlid": "ken.chung", "profileUrl": null}, {"staffid": "vera.chung", "givenname": "Vera", "surname": "Chung", "urlid": "vera.chung", "profileUrl": null}, {"staffid": "jacinta.cleary", "givenname": "Jacinta", "surname": "Cleary", "urlid": "jacinta.cleary", "profileUrl": null}, {"staffid": "m.cleary", "givenname": "Matthew", "surname": "Cleary", "urlid": "m.cleary", "profileUrl": null}, {"staffid": "scle4285", "givenname": "Stewart", "surname": "Clegg", "urlid": "scle4285", "profileUrl": null}, {"staffid": "hans.coster", "givenname": "Hans", "surname": "Coster", "urlid": "hans.coster", "profileUrl": null}, {"staffid": "lynn.crawford", "givenname": "Lynn", "surname": "Crawford", "urlid": "lynn.crawford", "profileUrl": null}, {"staffid": "mengying.cui", "givenname": "Mengying", "surname": "Cui", "urlid": "mengying.cui", "profileUrl": null}, {"staffid": "patrick.cullen", "givenname": "PJ", "surname": "Cullen", "urlid": "patrick.cullen", "profileUrl": null}, {"staffid": "john.currie", "givenname": "John", "surname": "Currie", "urlid": "john.currie", "profileUrl": null}, {"staffid": "marshall.dalton", "givenname": "Marshall", "surname": "Dalton", "urlid": "marshall.dalton", "profileUrl": null}, {"staffid": "donald.dansereau", "givenname": "Donald", "surname": "Dansereau", "urlid": "donald.dansereau", "profileUrl": null}, {"staffid": "joseph.davis", "givenname": "Joseph", "surname": "Davis", "urlid": "joseph.davis", "profileUrl": null}, {"staffid": "philip.dechazal", "givenname": "Philip", "surname": "de Chazal", "urlid": "philip.dechazal", "profileUrl": null}, {"staffid": "fariba.dehghani", "givenname": "Fariba", "surname": "Dehghani", "urlid": "fariba.dehghani", "profileUrl": null}, {"staffid": "daniel.diasdacosta", "givenname": "Daniel", "surname": "Dias Da Costa", "urlid": "daniel.diasdacosta", "profileUrl": null}, {"staffid": "tejaswi.digumarti", "givenname": "Sundara Tejaswi", "surname": "Digumarti", "urlid": "tejaswi.digumarti", "profileUrl": null}, {"staffid": "jia.ding", "givenname": "Jia", "surname": "Ding", "urlid": "jia.ding", "profileUrl": null}, {"staffid": "rafael.oliveira", "givenname": "Rafael", "surname": "Dos Santos De Oliveira", "urlid": "rafael.oliveira", "profileUrl": null}, {"staffid": "matthew.dunn", "givenname": "Matthew", "surname": "Dunn", "urlid": "matthew.dunn", "profileUrl": null}, {"staffid": "hugh.durrantwhyte", "givenname": "Hugh", "surname": "Durrant-Whyte", "urlid": "hugh.durrantwhyte", "profileUrl": null}, {"staffid": "peter.eades", "givenname": "Peter", "surname": "Eades", "urlid": "peter.eades", "profileUrl": null}, {"staffid": "amirali.ebrahimighadi", "givenname": "Amirali", "surname": "Ebrahimi Ghadi", "urlid": "amirali.ebrahimighadi", "profileUrl": null}, {"staffid": "itai.einav", "givenname": "Itai", "surname": "Einav", "urlid": "itai.einav", "profileUrl": null}, {"staffid": "abbas.elzein", "givenname": "Abbas", "surname": "El-Zein", "urlid": "abbas.elzein", "profileUrl": null}, {"staffid": "ali.entezari", "givenname": "Ali", "surname": "Entezari", "urlid": "ali.entezari", "profileUrl": null}, {"staffid": "youngho.eun", "givenname": "Youngho", "surname": "Eun", "urlid": "youngho.eun", "profileUrl": null}, {"staffid": "syamak.farajikhah", "givenname": "Syamak", "surname": "Farajikhah", "urlid": "syamak.farajikhah", "profileUrl": null}, {"staffid": "farnaz.farid", "givenname": "Farnaz", "surname": "Farid", "urlid": "farnaz.farid", "profileUrl": null}, {"staffid": "alan.fekete", "givenname": "Alan", "surname": "Fekete", "urlid": "alan.fekete", "profileUrl": null}, {"staffid": "dagan.feng", "givenname": "Dagan", "surname": "Feng", "urlid": "dagan.feng", "profileUrl": null}, {"staffid": "rod.fiford", "givenname": "Rodney", "surname": "Fiford", "urlid": "rod.fiford", "profileUrl": null}, {"staffid": "gustavo.fimbresweihs", "givenname": "Gustavo", "surname": "Fimbres Weihs", "urlid": "gustavo.fimbresweihs", "profileUrl": null}, {"staffid": "david.fletcher", "givenname": "David", "surname": "Fletcher", "urlid": "david.fletcher", "profileUrl": null}, {"staffid": "barry.flower", "givenname": "Barry", "surname": "Flower", "urlid": "barry.flower", "profileUrl": null}, {"staffid": "mehdi.foumani", "givenname": "Mehdi", "surname": "Foumani", "urlid": "mehdi.foumani", "profileUrl": null}, {"staffid": "damian.frank", "givenname": "Damian", "surname": "Frank", "urlid": "damian.frank", "profileUrl": null}, {"staffid": "michael.fulham", "givenname": "Michael", "surname": "Fulham", "urlid": "michael.fulham", "profileUrl": null}, {"staffid": "yixiang.gan", "givenname": "Yixiang", "surname": "Gan", "urlid": "yixiang.gan", "profileUrl": null}, {"staffid": "aaron.gilmour", "givenname": "Aaron", "surname": "Gilmour", "urlid": "aaron.gilmour", "profileUrl": null}, {"staffid": "ali.goktogan", "givenname": "Ali", "surname": "Goktogan", "urlid": "ali.goktogan", "profileUrl": null}, {"staffid": "tom.goldfinch", "givenname": "Tom", "surname": "Goldfinch", "urlid": "tom.goldfinch", "profileUrl": null}, {"staffid": "vincent.gomes", "givenname": "Vincent", "surname": "Gomes", "urlid": "vincent.gomes", "profileUrl": null}, {"staffid": "vincent.gramoli", "givenname": "Vincent", "surname": "Gramoli", "urlid": "vincent.gramoli", "profileUrl": null}, {"staffid": "matthew.griffith", "givenname": "Matthew", "surname": "Griffith", "urlid": "matthew.griffith", "profileUrl": null}, {"staffid": "michael.groom", "givenname": "Michael", "surname": "Groom", "urlid": "michael.groom", "profileUrl": null}, {"staffid": "yifan.gu", "givenname": "Yifan", "surname": "Gu", "urlid": "yifan.gu", "profileUrl": null}, {"staffid": "vijay.gudla", "givenname": "Vijaya", "surname": "Gudla", "urlid": "vijay.gudla", "profileUrl": null}, {"staffid": "joachim.gudmundsson", "givenname": "Joachim", "surname": "Gudmundsson", "urlid": "joachim.gudmundsson", "profileUrl": null}, {"staffid": "francois.guillard", "givenname": "Francois", "surname": "Guillard", "urlid": "francois.guillard", "profileUrl": null}, {"staffid": "philip.gun", "givenname": "Philip", "surname": "Gun", "urlid": "philip.gun", "profileUrl": null}, {"staffid": "ali.hadigheh", "givenname": "Ali", "surname": "Hadigheh", "urlid": "ali.hadigheh", "profileUrl": null}, {"staffid": "caren.han", "givenname": "Caren", "surname": "Han", "urlid": "caren.han", "profileUrl": null}, {"staffid": "gregory.hancock", "givenname": "Gregory", "surname": "Hancock", "urlid": "gregory.hancock", "profileUrl": null}, {"staffid": "wibowo.hardjawana", "givenname": "Wibowo", "surname": "Hardjawana", "urlid": "wibowo.hardjawana", "profileUrl": null}, {"staffid": "michael.harre", "givenname": "Michael", "surname": "Harre", "urlid": "michael.harre", "profileUrl": null}, {"staffid": "andrew.harris", "givenname": "Andrew", "surname": "Harris", "urlid": "andrew.harris", "profileUrl": null}, {"staffid": "rabiul.hasan", "givenname": "M. Rabiul", "surname": "Hasan", "urlid": "rabiul.hasan", "profileUrl": null}, {"staffid": "m.hassan", "givenname": "MD. Mahbub", "surname": "Hassan", "urlid": "m.hassan", "profileUrl": null}, {"staffid": "brian.haynes", "givenname": "Brian", "surname": "Haynes", "urlid": "brian.haynes", "profileUrl": null}, {"staffid": "daniel.hickmott", "givenname": "Daniel", "surname": "Hickmott", "urlid": "daniel.hickmott", "profileUrl": null}, {"staffid": "andrew.hill", "givenname": "Andrew", "surname": "Hill", "urlid": "andrew.hill", "profileUrl": null}, {"staffid": "david.hill", "givenname": "David", "surname": "Hill", "urlid": "david.hill", "profileUrl": null}, {"staffid": "ralph.holz", "givenname": "Ralph", "surname": "Holz", "urlid": "ralph.holz", "profileUrl": null}, {"staffid": "seokhee.hong", "givenname": "Seokhee", "surname": "Hong", "urlid": "seokhee.hong", "profileUrl": null}, {"staffid": "zhanwei.hou", "givenname": "Zhanwei", "surname": "Hou", "urlid": "zhanwei.hou", "profileUrl": null}, {"staffid": "jun.huang", "givenname": "Jun", "surname": "Huang", "urlid": "jun.huang", "profileUrl": null}, {"staffid": "shaoli.huang", "givenname": "Shaoli", "surname": "Huang", "urlid": "shaoli.huang", "profileUrl": null}, {"staffid": "viorela.ila", "givenname": "Viorela", "surname": "Ila", "urlid": "viorela.ila", "profileUrl": null}, {"staffid": "ahmad.jabbarzadeh", "givenname": "Ahmad", "surname": "Jabbarzadeh", "urlid": "ahmad.jabbarzadeh", "profileUrl": null}, {"staffid": "abbas.jamalipour", "givenname": "Abbas", "surname": "Jamalipour", "urlid": "abbas.jamalipour", "profileUrl": null}, {"staffid": "nicholas.james", "givenname": "Nicholas", "surname": "James", "urlid": "nicholas.james", "profileUrl": null}, {"staffid": "kamil.jezek", "givenname": "Kamil", "surname": "Jezek", "urlid": "kamil.jezek", "profileUrl": null}, {"staffid": "craig.jin", "givenname": "Craig", "surname": "Jin", "urlid": "craig.jin", "profileUrl": null}, {"staffid": "peter.jones", "givenname": "Peter", "surname": "Jones", "urlid": "peter.jones", "profileUrl": null}, {"staffid": "william.jones", "givenname": "William", "surname": "Jones", "urlid": "william.jones", "profileUrl": null}, {"staffid": "arnold.ju", "givenname": "Arnold Lining", "surname": "Ju", "urlid": "arnold.ju", "profileUrl": null}, {"staffid": "anthony.kadi", "givenname": "Anthony", "surname": "Kadi", "urlid": "anthony.kadi", "profileUrl": null}, {"staffid": "john.kavanagh", "givenname": "John", "surname": "Kavanagh", "urlid": "john.kavanagh", "profileUrl": null}, {"staffid": "omid.kavehei", "givenname": "Omid", "surname": "Kavehei", "urlid": "omid.kavehei", "profileUrl": null}, {"staffid": "judy.kay", "givenname": "Judith", "surname": "Kay", "urlid": "judy.kay", "profileUrl": null}, {"staffid": "mani.khezri", "givenname": "Mani", "surname": "Khezri", "urlid": "mani.khezri", "profileUrl": null}, {"staffid": "rami.khushaba", "givenname": "Rami", "surname": "Khushaba", "urlid": "rami.khushaba", "profileUrl": null}, {"staffid": "matloob.khushi", "givenname": "Matloob", "surname": "Khushi", "urlid": "matloob.khushi", "profileUrl": null}, {"staffid": "michael.kirkpatrick", "givenname": "Michael", "surname": "Kirkpatrick", "urlid": "michael.kirkpatrick", "profileUrl": null}, {"staffid": "he.kong", "givenname": "He", "surname": "Kong", "urlid": "he.kong", "profileUrl": null}, {"staffid": "irena.koprinska", "givenname": "Irena", "surname": "Koprinska", "urlid": "irena.koprinska", "profileUrl": null}, {"staffid": "agisilaos.kourmatzis", "givenname": "Agisilaos", "surname": "Kourmatzis", "urlid": "agisilaos.kourmatzis", "profileUrl": null}, {"staffid": "kevin.kuan", "givenname": "Kevin", "surname": "Kuan", "urlid": "kevin.kuan", "profileUrl": null}, {"staffid": "ashnil.kumar", "givenname": "Ashnil", "surname": "Kumar", "urlid": "ashnil.kumar", "profileUrl": null}, {"staffid": "bob.kummerfeld", "givenname": "Bob", "surname": "Kummerfeld", "urlid": "bob.kummerfeld", "profileUrl": null}, {"staffid": "kenny.kwok", "givenname": "Kenny", "surname": "Kwok", "urlid": "kenny.kwok", "profileUrl": null}, {"staffid": "andre.kyme", "givenname": "Andre", "surname": "Kyme", "urlid": "andre.kyme", "profileUrl": null}, {"staffid": "timothy.langrish", "givenname": "Timothy", "surname": "Langrish", "urlid": "timothy.langrish", "profileUrl": null}, {"staffid": "chengwang.lei", "givenname": "Chengwang", "surname": "Lei", "urlid": "chengwang.lei", "profileUrl": null}, {"staffid": "philip.leong", "givenname": "Philip Heng Wai", "surname": "Leong", "urlid": "philip.leong", "profileUrl": null}, {"staffid": "baptiste.lepers", "givenname": "Baptiste", "surname": "Lepers", "urlid": "baptiste.lepers", "profileUrl": null}, {"staffid": "david.levinson", "givenname": "David", "surname": "Levinson", "urlid": "david.levinson", "profileUrl": null}, {"staffid": "fengwang.li", "givenname": "Fengwang", "surname": "Li", "urlid": "fengwang.li", "profileUrl": null}, {"staffid": "liwei.li", "givenname": "Liwei", "surname": "Li", "urlid": "liwei.li", "profileUrl": null}, {"staffid": "qing.li", "givenname": "Qing", "surname": "Li", "urlid": "qing.li", "profileUrl": null}, {"staffid": "sinan.li", "givenname": "Sinan", "surname": "Li", "urlid": "sinan.li", "profileUrl": null}, {"staffid": "weiwilson.li", "givenname": "Wei", "surname": "Li", "urlid": "weiwilson.li", "profileUrl": null}, {"staffid": "yonghui.li", "givenname": "Yonghui", "surname": "Li", "urlid": "yonghui.li", "profileUrl": null}, {"staffid": "weibin.liang", "givenname": "Weibin", "surname": "Liang", "urlid": "weibin.liang", "profileUrl": null}, {"staffid": "xiaozhou.liao", "givenname": "Xiaozhou", "surname": "Liao", "urlid": "xiaozhou.liao", "profileUrl": null}, {"staffid": "tj.lim", "givenname": "Teng Joon", "surname": "Lim", "urlid": "tj.lim", "profileUrl": null}, {"staffid": "zihuai.lin", "givenname": "Zihuai", "surname": "Lin", "urlid": "zihuai.lin", "profileUrl": null}, {"staffid": "dongnan.liu", "givenname": "Daniel", "surname": "Liu", "urlid": "dongnan.liu", "profileUrl": null}, {"staffid": "hong-yuan.liu", "givenname": "Hong-Yuan", "surname": "Liu", "urlid": "hong-yuan.liu", "profileUrl": null}, {"staffid": "liu.liu1", "givenname": "Liu", "surname": "Liu", "urlid": "liu.liu1", "profileUrl": null}, {"staffid": "liyang.liu", "givenname": "Liyang", "surname": "Liu", "urlid": "liyang.liu", "profileUrl": null}, {"staffid": "tongliang.liu", "givenname": "Tongliang", "surname": "Liu", "urlid": "tongliang.liu", "profileUrl": null}, {"staffid": "wanchun.liu", "givenname": "Wanchun", "surname": "Liu", "urlid": "wanchun.liu", "profileUrl": null}, {"staffid": "zongwen.liu", "givenname": "Zongwen", "surname": "Liu", "urlid": "zongwen.liu", "profileUrl": null}, {"staffid": "joseph.lizier", "givenname": "Joseph", "surname": "Lizier", "urlid": "joseph.lizier", "profileUrl": null}, {"staffid": "martin.locke", "givenname": "Martin", "surname": "Locke", "urlid": "martin.locke", "profileUrl": null}, {"staffid": "alow2350", "givenname": "Albyn", "surname": "Lowe", "urlid": "alow2350", "profileUrl": null}, {"staffid": "david.lowe", "givenname": "David", "surname": "Lowe", "urlid": "david.lowe", "profileUrl": null}, {"staffid": "xinglong.lu", "givenname": "Xinglong", "surname": "Lu", "urlid": "xinglong.lu", "profileUrl": null}, {"staffid": "zufu.lu", "givenname": "Zufu", "surname": "Lu", "urlid": "zufu.lu", "profileUrl": null}, {"staffid": "fengji.luo", "givenname": "Fengji", "surname": "Luo", "urlid": "fengji.luo", "profileUrl": null}, {"staffid": "jinglei.lv", "givenname": "Jinglei", "surname": "Lv", "urlid": "jinglei.lv", "profileUrl": null}, {"staffid": "j.ma", "givenname": "Jin", "surname": "Ma", "urlid": "j.ma", "profileUrl": null}, {"staffid": "rens.macneill", "givenname": "Rens", "surname": "MacNeill", "urlid": "rens.macneill", "profileUrl": null}, {"staffid": "federico.maggi", "givenname": "Federico", "surname": "Maggi", "urlid": "federico.maggi", "profileUrl": null}, {"staffid": "yiu-wing.mai", "givenname": "Yiu-Wing", "surname": "Mai", "urlid": "yiu-wing.mai", "profileUrl": null}, {"staffid": "anne.mai-prochnow", "givenname": "Anne", "surname": "Mai-Prochnow", "urlid": "anne.mai-prochnow", "profileUrl": null}, {"staffid": "raffaella.mammucari", "givenname": "Raffaella", "surname": "Mammucari", "urlid": "raffaella.mammucari", "profileUrl": null}, {"staffid": "ian.manchester", "givenname": "Ian", "surname": "Manchester", "urlid": "ian.manchester", "profileUrl": null}, {"staffid": "roman.marchant", "givenname": "Roman", "surname": "Marchant", "urlid": "roman.marchant", "profileUrl": null}, {"staffid": "benjy.marks", "givenname": "Benjy", "surname": "Marks", "urlid": "benjy.marks", "profileUrl": null}, {"staffid": "david.martinezmartin", "givenname": "David", "surname": "Martinez Martin", "urlid": "david.martinezmartin", "profileUrl": null}, {"staffid": "assaad.masri", "givenname": "Assaad", "surname": "Masri", "urlid": "assaad.masri", "profileUrl": null}, {"staffid": "petr.matous", "givenname": "Petr", "surname": "Matous", "urlid": "petr.matous", "profileUrl": null}, {"staffid": "jessica.mcbroom.799", "givenname": "Jessica", "surname": "McBroom", "urlid": "jessica.mcbroom.799", "profileUrl": null}, {"staffid": "alistair.mcewan", "givenname": "Alistair", "surname": "McEwan", "urlid": "alistair.mcewan", "profileUrl": null}, {"staffid": "arman.melkumyan", "givenname": "Arman", "surname": "Melkumyan", "urlid": "arman.melkumyan", "profileUrl": null}, {"staffid": "julian.mestre", "givenname": "Julian", "surname": "Mestre", "urlid": "julian.mestre", "profileUrl": null}, {"staffid": "guien.miao", "givenname": "Guien", "surname": "Miao", "urlid": "guien.miao", "profileUrl": null}, {"staffid": "vera.miloslavskaya", "givenname": "Vera", "surname": "Miloslavskaya", "urlid": "vera.miloslavskaya", "profileUrl": null}, {"staffid": "robert.minasian", "givenname": "Robert", "surname": "Minasian", "urlid": "robert.minasian", "profileUrl": null}, {"staffid": "mohammad.mirkhalaf", "givenname": "Mohammad", "surname": "Mirkhalaf Valashani", "urlid": "mohammad.mirkhalaf", "profileUrl": null}, {"staffid": "alejandro.montoya", "givenname": "Alejandro", "surname": "Montoya", "urlid": "alejandro.montoya", "profileUrl": null}, {"staffid": "eman.mousavinejad", "givenname": "Eman", "surname": "Mousavinejad", "urlid": "eman.mousavinejad", "profileUrl": null}, {"staffid": "emily.moylan", "givenname": "Emily", "surname": "Moylan", "urlid": "emily.moylan", "profileUrl": null}, {"staffid": "mohanad.mursi", "givenname": "Mohanad", "surname": "Mursi", "urlid": "mohanad.mursi", "profileUrl": null}, {"staffid": "nnad8549", "givenname": "Nader", "surname": "Naderpajouh", "urlid": "nnad8549", "profileUrl": null}, {"staffid": "sina.naficy", "givenname": "Sina", "surname": "Naficy", "urlid": "sina.naficy", "profileUrl": null}, {"staffid": "karan.narula", "givenname": "Karan", "surname": "Narula", "urlid": "karan.narula", "profileUrl": null}, {"staffid": "eduardo.nebot", "givenname": "Eduardo", "surname": "Nebot", "urlid": "eduardo.nebot", "profileUrl": null}, {"staffid": "jianlei.niu", "givenname": "Jianlei", "surname": "Niu", "urlid": "jianlei.niu", "profileUrl": null}, {"staffid": "ranming.niu", "givenname": "Ranming", "surname": "Niu", "urlid": "ranming.niu", "profileUrl": null}, {"staffid": "young.no", "givenname": "Young", "surname": "No", "urlid": "young.no", "profileUrl": null}, {"staffid": "aaron.opdyke", "givenname": "Aaron", "surname": "Opdyke", "urlid": "aaron.opdyke", "profileUrl": null}, {"staffid": "wanli.ouyang", "givenname": "Wanli", "surname": "Ouyang", "urlid": "wanli.ouyang", "profileUrl": null}, {"staffid": "farshad.oveissi", "givenname": "Farshad", "surname": "Oveissi", "urlid": "farshad.oveissi", "profileUrl": null}, {"staffid": "john.papangelis", "givenname": "John", "surname": "Papangelis", "urlid": "john.papangelis", "profileUrl": null}, {"staffid": "john.patterson", "givenname": "John", "surname": "Patterson", "urlid": "john.patterson", "profileUrl": null}, {"staffid": "zengxia.pei", "givenname": "Zengxia", "surname": "Pei", "urlid": "zengxia.pei", "profileUrl": null}, {"staffid": "neysa.petrina", "givenname": "Maria", "surname": "Petrina", "urlid": "neysa.petrina", "profileUrl": null}, {"staffid": "caohung.pham", "givenname": "Cao Hung", "surname": "Pham", "urlid": "caohung.pham", "profileUrl": null}, {"staffid": "mahendrarajah.piraveenan", "givenname": "Mahendra", "surname": "Piraveenan", "urlid": "mahendrarajah.piraveenan", "profileUrl": null}, {"staffid": "oscar.pizarro", "givenname": "Oscar", "surname": "Pizarro", "urlid": "oscar.pizarro", "profileUrl": null}, {"staffid": "masbaul.polash", "givenname": "Mohammad", "surname": "Polash", "urlid": "masbaul.polash", "profileUrl": null}, {"staffid": "julien.pollack", "givenname": "Julien", "surname": "Pollack", "urlid": "julien.pollack", "profileUrl": null}, {"staffid": "josiah.poon", "givenname": "Josiah", "surname": "Poon", "urlid": "josiah.poon", "profileUrl": null}, {"staffid": "simon.poon", "givenname": "Simon", "surname": "Poon", "urlid": "simon.poon", "profileUrl": null}, {"staffid": "harry.poulos", "givenname": "Harry", "surname": "Poulos", "urlid": "harry.poulos", "profileUrl": null}, {"staffid": "mikhail.prokopenko", "givenname": "Mikhail", "surname": "Prokopenko", "urlid": "mikhail.prokopenko", "profileUrl": null}, {"staffid": "gwenaelle.proust", "givenname": "Gwenaelle", "surname": "Proust", "urlid": "gwenaelle.proust", "profileUrl": null}, {"staffid": "abdul.qadir", "givenname": "Abdul", "surname": "Qadir", "urlid": "abdul.qadir", "profileUrl": null}, {"staffid": "yongliang.qiao", "givenname": "Yongliang", "surname": "Qiao", "urlid": "yongliang.qiao", "profileUrl": null}, {"staffid": "jeremy.qiu", "givenname": "Jeremy (Jing)", "surname": "Qiu", "urlid": "jeremy.qiu", "profileUrl": null}, {"staffid": "gobinath.rajarathnam", "givenname": "Gobinath", "surname": "Rajarathnam", "urlid": "gobinath.rajarathnam", "profileUrl": null}, {"staffid": "yogambha.ramaswamy", "givenname": "Yogambha", "surname": "Ramaswamy", "urlid": "yogambha.ramaswamy", "profileUrl": null}, {"staffid": "mohsen.ramezani", "givenname": "Mohsen", "surname": "Ramezani", "urlid": "mohsen.ramezani", "profileUrl": null}, {"staffid": "fabio.ramos", "givenname": "Fabio", "surname": "Ramos", "urlid": "fabio.ramos", "profileUrl": null}, {"staffid": "gianluca.ranzi", "givenname": "Gianluca", "surname": "Ranzi", "urlid": "gianluca.ranzi", "profileUrl": null}, {"staffid": "kim.rasmussen", "givenname": "Kim", "surname": "Rasmussen", "urlid": "kim.rasmussen", "profileUrl": null}, {"staffid": "mark.read", "givenname": "Mark", "surname": "Read", "urlid": "mark.read", "profileUrl": null}, {"staffid": "uwe.roehm", "givenname": "Uwe", "surname": "Roehm", "urlid": "uwe.roehm", "profileUrl": null}, {"staffid": "pierre.rognon", "givenname": "Pierre", "surname": "Rognon", "urlid": "pierre.rognon", "profileUrl": null}, {"staffid": "sasha.rubin", "givenname": "Sasha", "surname": "Rubin", "urlid": "sasha.rubin", "profileUrl": null}, {"staffid": "david.rye", "givenname": "David", "surname": "Rye", "urlid": "david.rye", "profileUrl": null}, {"staffid": "mohammad.saadatfar", "givenname": "Mohammad", "surname": "Saadatfar", "urlid": "mohammad.saadatfar", "profileUrl": null}, {"staffid": "ehssan.sakhaee", "givenname": "Ehssan", "surname": "Sakhaee", "urlid": "ehssan.sakhaee", "profileUrl": null}, {"staffid": "s.sathiakumar", "givenname": "Swamidoss", "surname": "Sathiakumar", "urlid": "s.sathiakumar", "profileUrl": null}, {"staffid": "aaron.schindeler", "givenname": "Aaron", "surname": "Schindeler", "urlid": "aaron.schindeler", "profileUrl": null}, {"staffid": "bernhard.scholz", "givenname": "Bernhard", "surname": "Scholz", "urlid": "bernhard.scholz", "profileUrl": null}, {"staffid": "konstantin.seiler", "givenname": "Konstantin", "surname": "Seiler", "urlid": "konstantin.seiler", "profileUrl": null}, {"staffid": "suranga.seneviratne", "givenname": "Suranga", "surname": "Seneviratne", "urlid": "suranga.seneviratne", "profileUrl": null}, {"staffid": "martin.seybold", "givenname": "Martin", "surname": "Seybold", "urlid": "martin.seybold", "profileUrl": null}, {"staffid": "chuhan.sha", "givenname": "Chuhan", "surname": "Sha", "urlid": "chuhan.sha", "profileUrl": null}, {"staffid": "mahdi.shahmoradi", "givenname": "Mahdi", "surname": "Shahmoradi", "urlid": "mahdi.shahmoradi", "profileUrl": null}, {"staffid": "mao.shan", "givenname": "Mao", "surname": "Shan", "urlid": "mao.shan", "profileUrl": null}, {"staffid": "luming.shen", "givenname": "Luming", "surname": "Shen", "urlid": "luming.shen", "profileUrl": null}, {"staffid": "yi.shen", "givenname": "Yi", "surname": "Shen", "urlid": "yi.shen", "profileUrl": null}, {"staffid": "guodong.shi", "givenname": "Guodong", "surname": "Shi", "urlid": "guodong.shi", "profileUrl": null}, {"staffid": "jeff.shi", "givenname": "Jeffrey", "surname": "Shi", "urlid": "jeff.shi", "profileUrl": null}, {"staffid": "mahyar.shirvanimoghaddam", "givenname": "Mahyar", "surname": "Shirvanimoghaddam", "urlid": "mahyar.shirvanimoghaddam", "profileUrl": null}, {"staffid": "david.shorten", "givenname": "David", "surname": "Shorten", "urlid": "david.shorten", "profileUrl": null}, {"staffid": "yash.shrivastava", "givenname": "Yash", "surname": "Shrivastava", "urlid": "yash.shrivastava", "profileUrl": null}, {"staffid": "katherine.silversides", "givenname": "Katherine", "surname": "Silversides", "urlid": "katherine.silversides", "profileUrl": null}, {"staffid": "gurvinder.singh", "givenname": "Gurvinder", "surname": "Singh", "urlid": "gurvinder.singh", "profileUrl": null}, {"staffid": "behdad.soltani", "givenname": "Behdad", "surname": "Soltani", "urlid": "behdad.soltani", "profileUrl": null}, {"staffid": "shuaiwen.song", "givenname": "Shuaiwen", "surname": "Song", "urlid": "shuaiwen.song", "profileUrl": null}, {"staffid": "john.stavrakakis", "givenname": "John", "surname": "Stavrakakis", "urlid": "john.stavrakakis", "profileUrl": null}, {"staffid": "gregg.suaning", "givenname": "Gregg", "surname": "Suaning", "urlid": "gregg.suaning", "profileUrl": null}, {"staffid": "salah.sukkarieh", "givenname": "Salah", "surname": "Sukkarieh", "urlid": "salah.sukkarieh", "profileUrl": null}, {"staffid": "basem.suleiman", "givenname": "Basem", "surname": "Suleiman", "urlid": "basem.suleiman", "profileUrl": null}, {"staffid": "michael.swain", "givenname": "Michael", "surname": "Swain", "urlid": "michael.swain", "profileUrl": null}, {"staffid": "masa.takatsuka", "givenname": "Masahiro", "surname": "Takatsuka", "urlid": "masa.takatsuka", "profileUrl": null}, {"staffid": "qiang.tang", "givenname": "Qiang", "surname": "Tang", "urlid": "qiang.tang", "profileUrl": null}, {"staffid": "roger.tanner", "givenname": "Roger", "surname": "Tanner", "urlid": "roger.tanner", "profileUrl": null}, {"staffid": "dacheng.tao", "givenname": "Dacheng", "surname": "Tao", "urlid": "dacheng.tao", "profileUrl": null}, {"staffid": "levi.tegg", "givenname": "Levi", "surname": "Tegg", "urlid": "levi.tegg", "profileUrl": null}, {"staffid": "kanchana.thilakarathna", "givenname": "Kanchana", "surname": "Thilakarathna", "urlid": "kanchana.thilakarathna", "profileUrl": null}, {"staffid": "jacqueline.thomas", "givenname": "Jacqueline", "surname": "Thomas", "urlid": "jacqueline.thomas", "profileUrl": null}, {"staffid": "ben.thornber", "givenname": "Ben", "surname": "Thornber", "urlid": "ben.thornber", "profileUrl": null}, {"staffid": "liyong.tong", "givenname": "Liyong", "surname": "Tong", "urlid": "liyong.tong", "profileUrl": null}, {"staffid": "lachlan.toohey", "givenname": "Lachlan", "surname": "Toohey", "urlid": "lachlan.toohey", "profileUrl": null}, {"staffid": "clara.tran", "givenname": "Clara", "surname": "Tran", "urlid": "clara.tran", "profileUrl": null}, {"staffid": "nguyen.tran", "givenname": "Nguyen", "surname": "Tran", "urlid": "nguyen.tran", "profileUrl": null}, {"staffid": "antonio.tricoli", "givenname": "Antonio", "surname": "Tricoli", "urlid": "antonio.tricoli", "profileUrl": null}, {"staffid": "duy.truong", "givenname": "Nhan", "surname": "Truong", "urlid": "duy.truong", "profileUrl": null}, {"staffid": "shahadat.uddin", "givenname": "Shahadat", "surname": "Uddin", "urlid": "shahadat.uddin", "profileUrl": null}, {"staffid": "giulia.ulpiani", "givenname": "Giulia", "surname": "Ulpiani", "urlid": "giulia.ulpiani", "profileUrl": null}, {"staffid": "william.umboh", "givenname": "William", "surname": "Umboh", "urlid": "william.umboh", "profileUrl": null}, {"staffid": "brian.uy", "givenname": "Brian", "surname": "Uy", "urlid": "brian.uy", "profileUrl": null}, {"staffid": "marjorie.valix", "givenname": "Marjorie", "surname": "Valix", "urlid": "marjorie.valix", "profileUrl": null}, {"staffid": "peter.valtchev", "givenname": "Peter", "surname": "Valtchev", "urlid": "peter.valtchev", "profileUrl": null}, {"staffid": "andre.vanrenssen", "givenname": "Andre", "surname": "van Renssen", "urlid": "andre.vanrenssen", "profileUrl": null}, {"staffid": "gregor.verbic", "givenname": "Gregor", "surname": "Verbic", "urlid": "gregor.verbic", "profileUrl": null}, {"staffid": "dries.verstraete", "givenname": "Dries", "surname": "Verstraete", "urlid": "dries.verstraete", "profileUrl": null}, {"staffid": "daniele.vigolo", "givenname": "Daniele", "surname": "Vigolo", "urlid": "daniele.vigolo", "profileUrl": null}, {"staffid": "gareth.vio", "givenname": "Gareth", "surname": "Vio", "urlid": "gareth.vio", "profileUrl": null}, {"staffid": "branka.vucetic", "givenname": "Branka", "surname": "Vucetic", "urlid": "branka.vucetic", "profileUrl": null}, {"staffid": "nathan.wallace", "givenname": "Nathan", "surname": "Wallace", "urlid": "nathan.wallace", "profileUrl": null}, {"staffid": "bosen.wang", "givenname": "Bosen", "surname": "Wang", "urlid": "bosen.wang", "profileUrl": null}, {"staffid": "chaoyue.wang", "givenname": "Chaoyue", "surname": "Wang", "urlid": "chaoyue.wang", "profileUrl": null}, {"staffid": "david.wang1", "givenname": "David", "surname": "Wang", "urlid": "david.wang1", "profileUrl": null}, {"staffid": "lei.wang2", "givenname": "Lei", "surname": "Wang", "urlid": "lei.wang2", "profileUrl": null}, {"staffid": "thomaspeng.wang", "givenname": "Peng", "surname": "Wang", "urlid": "thomaspeng.wang", "profileUrl": null}, {"staffid": "ruigang.wang", "givenname": "Ruigang", "surname": "Wang", "urlid": "ruigang.wang", "profileUrl": null}, {"staffid": "xiu.wang", "givenname": "Xiu", "surname": "Wang", "urlid": "xiu.wang", "profileUrl": null}, {"staffid": "zhiyong.wang", "givenname": "Zhiyong", "surname": "Wang", "urlid": "zhiyong.wang", "profileUrl": null}, {"staffid": "greg.watkins", "givenname": "Greg", "surname": "Watkins", "urlid": "greg.watkins", "profileUrl": null}, {"staffid": "l.wei", "givenname": "Li", "surname": "Wei", "urlid": "l.wei", "profileUrl": null}, {"staffid": "dianne.wiley", "givenname": "Dianne", "surname": "Wiley", "urlid": "dianne.wiley", "profileUrl": null}, {"staffid": "tim.wilkinson", "givenname": "Tim", "surname": "Wilkinson", "urlid": "tim.wilkinson", "profileUrl": null}, {"staffid": "keith.willey", "givenname": "Keith", "surname": "Willey", "urlid": "keith.willey", "profileUrl": null}, {"staffid": "stefan.williams", "givenname": "Stefan", "surname": "Williams", "urlid": "stefan.williams", "profileUrl": null}, {"staffid": "nicholas.williamson", "givenname": "Nicholas", "surname": "Williamson", "urlid": "nicholas.williamson", "profileUrl": null}, {"staffid": "anusha.withana", "givenname": "Anusha", "surname": "Withana", "urlid": "anusha.withana", "profileUrl": null}, {"staffid": "kc.wong", "givenname": "KC", "surname": "Wong", "urlid": "kc.wong", "profileUrl": null}, {"staffid": "stewart.worrall", "givenname": "Stewart", "surname": "Worrall", "urlid": "stewart.worrall", "profileUrl": null}, {"staffid": "hao.wu1", "givenname": "Hao", "surname": "Wu", "urlid": "hao.wu1", "profileUrl": null}, {"staffid": "jiadai.wu", "givenname": "Jiadai", "surname": "Wu", "urlid": "jiadai.wu", "profileUrl": null}, {"staffid": "xi.wu", "givenname": "Xi", "surname": "Wu", "urlid": "xi.wu", "profileUrl": null}, {"staffid": "xiaofeng.wu", "givenname": "Xiaofeng", "surname": "Wu", "urlid": "xiaofeng.wu", "profileUrl": null}, {"staffid": "weidong.xiao", "givenname": "Weidong", "surname": "Xiao", "urlid": "weidong.xiao", "profileUrl": null}, {"staffid": "c.xu", "givenname": "Chang", "surname": "Xu", "urlid": "c.xu", "profileUrl": null}, {"staffid": "dong.xu", "givenname": "Dong", "surname": "Xu", "urlid": "dong.xu", "profileUrl": null}, {"staffid": "kalina.yacef", "givenname": "Kalina", "surname": "Yacef", "urlid": "kalina.yacef", "profileUrl": null}, {"staffid": "lin.ye", "givenname": "Lin", "surname": "Ye", "urlid": "lin.ye", "profileUrl": null}, {"staffid": "phee.yeoh", "givenname": "Phee", "surname": "Yeoh", "urlid": "phee.yeoh", "profileUrl": null}, {"staffid": "bowen.yi", "givenname": "Bowen", "surname": "Yi", "urlid": "bowen.yi", "profileUrl": null}, {"staffid": "xiaoke.yi", "givenname": "Xiaoke", "surname": "Yi", "urlid": "xiaoke.yi", "profileUrl": null}, {"staffid": "ken.yong", "givenname": "Ken Tye", "surname": "Yong", "urlid": "ken.yong", "profileUrl": null}, {"staffid": "soojeong.yoo", "givenname": "Soojeong", "surname": "Yoo", "urlid": "soojeong.yoo", "profileUrl": null}, {"staffid": "baosheng.yu", "givenname": "Baosheng", "surname": "Yu", "urlid": "baosheng.yu", "profileUrl": null}, {"staffid": "dong.yuan", "givenname": "Dong", "surname": "Yuan", "urlid": "dong.yuan", "profileUrl": null}, {"staffid": "hao.zhang", "givenname": "Hao", "surname": "Zhang", "urlid": "hao.zhang", "profileUrl": null}, {"staffid": "jing.zhang1", "givenname": "Jing", "surname": "Zhang", "urlid": "jing.zhang1", "profileUrl": null}, {"staffid": "shenlong.zhao", "givenname": "Shenlong", "surname": "Zhao", "urlid": "shenlong.zhao", "profileUrl": null}, {"staffid": "weiming.zhi", "givenname": "William", "surname": "Zhi", "urlid": "weiming.zhi", "profileUrl": null}, {"staffid": "bing.zhou", "givenname": "Bing", "surname": "Zhou", "urlid": "bing.zhou", "profileUrl": null}, {"staffid": "luping.zhou", "givenname": "Luping", "surname": "Zhou", "urlid": "luping.zhou", "profileUrl": null}, {"staffid": "renwu.zhou", "givenname": "Renwu", "surname": "Zhou", "urlid": "renwu.zhou", "profileUrl": null}, {"staffid": "ying.zhou", "givenname": "Ying", "surname": "Zhou", "urlid": "ying.zhou", "profileUrl": null}, {"staffid": "jianguo.zhu", "givenname": "Jian Guo", "surname": "Zhu", "urlid": "jianguo.zhu", "profileUrl": null}, {"staffid": "suqin.zhu", "givenname": "Suqin", "surname": "Zhu", "urlid": "suqin.zhu", "profileUrl": null}, {"staffid": "anna.paradowska", "givenname": "Anna", "surname": "Ziara-Paradowska", "urlid": "anna.paradowska", "profileUrl": null}, {"staffid": "albert.zomaya", "givenname": "Albert", "surname": "Zomaya", "urlid": "albert.zomaya", "profileUrl": null}, {"staffid": "hala.zreiqat", "givenname": "Hala", "surname": "Zreiqat", "urlid": "hala.zreiqat", "profileUrl": null}, {"staffid": "willy.zwaenepoel", "givenname": "Willy", "surname": "Zwaenepoel", "urlid": "willy.zwaenepoel", "profileUrl": null}]}
]